README.rst
setup.py
src/keepserver.py
src/keepserver.egg-info/PKG-INFO
src/keepserver.egg-info/SOURCES.txt
src/keepserver.egg-info/dependency_links.txt
src/keepserver.egg-info/entry_points.txt
src/keepserver.egg-info/requires.txt
src/keepserver.egg-info/top_level.txt
test/tests.py