Metadata-Version: 1.1
Name: keepserver
Version: 0.2.0
Summary: Monitor keepalived status, run start.sh if server get MASTER role, and run stop.sh if server get SLAVE role.
Home-page: https://github.com/appstore-zencore/keepserver
Author: zencore
Author-email: dobetter@zencore.cn
License: MIT
Keywords: keepserver
Platform: UNKNOWN
Classifier: Development Status :: 5 - Production/Stable
Classifier: Intended Audience :: Developers
Classifier: Topic :: Software Development :: Libraries :: Python Modules
Classifier: License :: OSI Approved :: MIT License
Classifier: Programming Language :: Python :: 3
Classifier: Programming Language :: Python :: 3 :: Only
Requires: psutil
Requires: dictop
Requires: appserver
